odoo8_addon_shopinvader_promotion_rule-8.0.1.0.0.99.dev1-py3.8-nspkg.pth
odoo_addons/shopinvader_promotion_rule/README.rst
odoo_addons/shopinvader_promotion_rule/__init__.py
odoo_addons/shopinvader_promotion_rule/__openerp__.py
odoo_addons/shopinvader_promotion_rule/services/__init__.py
odoo_addons/shopinvader_promotion_rule/services/cart.py
odoo_addons/shopinvader_promotion_rule/services/cart_item.py
odoo_addons/shopinvader_promotion_rule/tests/__init__.py
odoo_addons/shopinvader_promotion_rule/tests/test_promotion.py
odoo8_addon_shopinvader_promotion_rule-8.0.1.0.0.99.dev1.dist-info/METADATA
odoo8_addon_shopinvader_promotion_rule-8.0.1.0.0.99.dev1.dist-info/WHEEL
odoo8_addon_shopinvader_promotion_rule-8.0.1.0.0.99.dev1.dist-info/namespace_packages.txt
odoo8_addon_shopinvader_promotion_rule-8.0.1.0.0.99.dev1.dist-info/top_level.txt
odoo8_addon_shopinvader_promotion_rule-8.0.1.0.0.99.dev1.dist-info/RECORD
